setup.py
telestatsd/__init__.py
telestatsd.egg-info/PKG-INFO
telestatsd.egg-info/SOURCES.txt
telestatsd.egg-info/dependency_links.txt
telestatsd.egg-info/not-zip-safe
telestatsd.egg-info/requires.txt
telestatsd.egg-info/top_level.txt
telestatsd/address_providers/__init__.py
telestatsd/address_providers/inet.py
telestatsd/address_providers/srvinet.py
telestatsd/clients/__init__.py
telestatsd/clients/logger.py
telestatsd/clients/null.py
telestatsd/clients/udp.py