Metadata-Version: 1.1
Name: telestatsd
Version: 0.0.9
Summary: StatsD client in Python with support for Telegraf and SRV records in DNS
Home-page: https://github.com/operasoftware/telestatsd/
Author: Opera Wrocław Services
Author-email: svc-code@opera.com
License: MIT
Download-URL: https://github.com/operasoftware/telestatsd/tarball/0.0.9
Keywords: statsd telegraf srv service record
Platform: UNKNOWN
